fast_phonetic-0.1.0.dist-info/METADATA
fast_phonetic-0.1.0.dist-info/WHEEL
fast_phonetic-0.1.0.dist-info/license_files/LICENSE.txt
fast_phonetic/__init__.py
fast_phonetic/fast_phonetic.cpython-311-x86_64-linux-gnu.so
fast_phonetic-0.1.0.dist-info/RECORD
